{
  "project_info": {
    "project_number": "767577416347",
    "project_id": "lealzy",
    "storage_bucket": "lealzy.appspot.com"
  },
  "client": [
    {
      "client_info": {
        "mobilesdk_app_id": "1:767577416347:android:eaba8187317f7044015c3e",
        "android_client_info": {
          "package_name": "com.lealzy.business"
        }
      },
      "oauth_client": [
        {
          "client_id": "767577416347-4keb3n84u5p7dudioij4m7e2hjcqclrj.apps.googleusercontent.com",
          "client_type": 3
        }
      ],
      "api_key": [
        {
          "current_key": "AIzaSyCK5KrH6VUMCUFRvlhZ4nxFkRpRv4C3Etk"
        }
      ],
      "services": {
        "appinvite_service": {
          "other_platform_oauth_client": [
            {
              "client_id": "767577416347-4keb3n84u5p7dudioij4m7e2hjcqclrj.apps.googleusercontent.com",
              "client_type": 3
            },
            {
              "client_id": "767577416347-gjogb374go2080rc48gh1ocv631fsukf.apps.googleusercontent.com",
              "client_type": 2,
              "ios_info": {
                "bundle_id": "com.lealzy.business",
                "app_store_id": "1570965617"
              }
            }
          ]
        }
      }
    },
    {
      "client_info": {
        "mobilesdk_app_id": "1:767577416347:android:7198da1d067be4ff015c3e",
        "android_client_info": {
          "package_name": "com.lealzy.customer"
        }
      },
      "oauth_client": [
        {
          "client_id": "767577416347-4keb3n84u5p7dudioij4m7e2hjcqclrj.apps.googleusercontent.com",
          "client_type": 3
        }
      ],
      "api_key": [
        {
          "current_key": "AIzaSyCK5KrH6VUMCUFRvlhZ4nxFkRpRv4C3Etk"
        }
      ],
      "services": {
        "appinvite_service": {
          "other_platform_oauth_client": [
            {
              "client_id": "767577416347-4keb3n84u5p7dudioij4m7e2hjcqclrj.apps.googleusercontent.com",
              "client_type": 3
            },
            {
              "client_id": "767577416347-gjogb374go2080rc48gh1ocv631fsukf.apps.googleusercontent.com",
              "client_type": 2,
              "ios_info": {
                "bundle_id": "com.lealzy.business",
                "app_store_id": "1570965617"
              }
            }
          ]
        }
      }
    }
  ],
  "configuration_version": "1"
}
